clustrous/__init__.py
clustrous/_periodic_cluster.so
clustrous/cluster.py
clustrous/_periodic_cluster.so.dSYM/Contents/Info.plist
clustrous/_periodic_cluster.so.dSYM/Contents/Resources/DWARF/_periodic_cluster.so
clustrous-0.1.2.dist-info/DESCRIPTION.rst
clustrous-0.1.2.dist-info/METADATA
clustrous-0.1.2.dist-info/metadata.json
clustrous-0.1.2.dist-info/pbr.json
clustrous-0.1.2.dist-info/RECORD
clustrous-0.1.2.dist-info/top_level.txt
clustrous-0.1.2.dist-info/WHEEL
